bihulib/__init__.py
bihulib/bihulib.py
bihulib-1.1.1.dist-info/METADATA
bihulib-1.1.1.dist-info/WHEEL
bihulib-1.1.1.dist-info/top_level.txt
bihulib-1.1.1.dist-info/RECORD
