Metadata-Version: 2.1
Name: bihulib
Version: 1.1.1
Summary: bihu.com lib
Home-page: https://bihu.com/people/1052858039
Author: QQQQQ
Author-email: 15166054530@163.com
License: UNKNOWN
Platform: UNKNOWN
Classifier: Development Status :: 5 - Production/Stable
Classifier: Intended Audience :: Developers
Classifier: Natural Language :: English
Classifier: Programming Language :: Python
Classifier: Programming Language :: Python :: 3
Classifier: Programming Language :: Python :: 3.4
Classifier: Programming Language :: Python :: 3.5
Classifier: Programming Language :: Python :: 3.6
Classifier: Programming Language :: Python :: 3.7
Classifier: Programming Language :: Python :: 3.8
Classifier: Programming Language :: Python :: Implementation :: CPython
Classifier: Programming Language :: Python :: Implementation :: PyPy
Requires-Python: >=3.0, !=3.0.*, !=3.1.*, !=3.2.*, !=3.3*
Requires-Dist: requests (>=2.23.0)
